<OpenViBE-Scenario>
	<Boxes>
		<Box>
			<Identifier>(0x2c6cd881, 0x0ab87e9c)</Identifier>
			<Name>Generic stream reader</Name>
			<AlgorithmClassIdentifier>(0x6468099f, 0x0370095a)</AlgorithmClassIdentifier>
			<Outputs>
				<Output>
					<TypeIdentifier>(0x5ba36127, 0x195feae1)</TypeIdentifier>
					<Name>Output stream 1</Name>
				</Output>
			</Outputs>
			<Settings>
				<Setting>
					<TypeIdentifier>(0x330306dd, 0x74a95f98)</TypeIdentifier>
					<Name>Filename</Name>
					<DefaultValue></DefaultValue>
					<Value>${Path_Samples}/signals/bci-motor-imagery.ov</Value>
				</Setting>
			</Settings>
			<Attributes>
				<Attribute>
					<Identifier>(0x17ee7c08, 0x94c14893)</Identifier>
					<Value></Value>
				</Attribute>
				<Attribute>
					<Identifier>(0x1fa7a38f, 0x54edbe0b)</Identifier>
					<Value>96</Value>
				</Attribute>
				<Attribute>
					<Identifier>(0x1fa963f5, 0x1a638cd4)</Identifier>
					<Value>38</Value>
				</Attribute>
				<Attribute>
					<Identifier>(0x207c9054, 0x3c841b63)</Identifier>
					<Value>304</Value>
				</Attribute>
				<Attribute>
					<Identifier>(0x30a4e5c9, 0x83502953)</Identifier>
					<Value></Value>
				</Attribute>
				<Attribute>
					<Identifier>(0x4e7b798a, 0x183beafb)</Identifier>
					<Value>(0xf37b8e7a, 0x1bc33e4e)</Value>
				</Attribute>
				<Attribute>
					<Identifier>(0xad100179, 0xa3c984ab)</Identifier>
					<Value>177</Value>
				</Attribute>
				<Attribute>
					<Identifier>(0xc46b3d00, 0x3e0454e1)</Identifier>
					<Value>(0x00000000, 0x01b25f63)</Value>
				</Attribute>
				<Attribute>
					<Identifier>(0xc67a01dc, 0x28ce06c1)</Identifier>
					<Value></Value>
				</Attribute>
			</Attributes>
		</Box>
		<Box>
			<Identifier>(0x56fa5c33, 0x42722a79)</Identifier>
			<Name>Signal display</Name>
			<AlgorithmClassIdentifier>(0x0055be5f, 0x087bdd12)</AlgorithmClassIdentifier>
			<Inputs>
				<Input>
					<TypeIdentifier>(0x544a003e, 0x6dcba5f6)</TypeIdentifier>
					<Name>Signal</Name>
				</Input>
				<Input>
					<TypeIdentifier>(0x6f752dd0, 0x082a321e)</TypeIdentifier>
					<Name>Stimulations</Name>
				</Input>
			</Inputs>
			<Settings>
				<Setting>
					<TypeIdentifier>(0x512a166f, 0x5c3ef83f)</TypeIdentifier>
					<Name>Time Scale</Name>
					<DefaultValue>10</DefaultValue>
					<Value>10</Value>
				</Setting>
				<Setting>
					<TypeIdentifier>(0x5de046a6, 0x086340aa)</TypeIdentifier>
					<Name>Display Mode</Name>
					<DefaultValue>Scan</DefaultValue>
					<Value>Scan</Value>
				</Setting>
			</Settings>
			<Attributes>
				<Attribute>
					<Identifier>(0x1fa7a38f, 0x54edbe0b)</Identifier>
					<Value>160</Value>
				</Attribute>
				<Attribute>
					<Identifier>(0x1fa963f5, 0x1a638cd4)</Identifier>
					<Value>25</Value>
				</Attribute>
				<Attribute>
					<Identifier>(0x207c9054, 0x3c841b63)</Identifier>
					<Value>304</Value>
				</Attribute>
				<Attribute>
					<Identifier>(0x4e7b798a, 0x183beafb)</Identifier>
					<Value>(0x7c0a7486, 0x60bc938c)</Value>
				</Attribute>
				<Attribute>
					<Identifier>(0xad100179, 0xa3c984ab)</Identifier>
					<Value>109</Value>
				</Attribute>
			</Attributes>
		</Box>
	</Boxes>
	<Links>
		<Link>
			<Identifier>(0x5619d775, 0x1885eb9b)</Identifier>
			<Source>
				<BoxIdentifier>(0x2c6cd881, 0x0ab87e9c)</BoxIdentifier>
				<BoxOutputIndex>0</BoxOutputIndex>
			</Source>
			<Target>
				<BoxIdentifier>(0x56fa5c33, 0x42722a79)</BoxIdentifier>
				<BoxInputIndex>0</BoxInputIndex>
			</Target>
			<Attributes>
				<Attribute>
					<Identifier>(0x1b32c44c, 0x1905e0e9)</Identifier>
					<Value>121</Value>
				</Attribute>
				<Attribute>
					<Identifier>(0x358ae8b5, 0x0f8bacd1)</Identifier>
					<Value>304</Value>
				</Attribute>
				<Attribute>
					<Identifier>(0x3f0a3b27, 0x570913d2)</Identifier>
					<Value>143</Value>
				</Attribute>
				<Attribute>
					<Identifier>(0x6267b5c5, 0x676e3e42)</Identifier>
					<Value>297</Value>
				</Attribute>
			</Attributes>
		</Link>
	</Links>
	<VisualisationTree>
		<VisualisationWidget>
			<Identifier>(0x2c686488, 0x33321410)</Identifier>
			<Type>3</Type>
			<ParentIdentifier>(0xffffffff, 0xffffffff)</ParentIdentifier>
			<BoxIdentifier>(0x56fa5c33, 0x42722a79)</BoxIdentifier>
			<NumChildren>0</NumChildren>
		</VisualisationWidget>
		<VisualisationWidget>
			<Identifier>(0x77dc7174, 0x49113dde)</Identifier>
			<Name>Default window</Name>
			<Type>1</Type>
			<ParentIdentifier>(0xffffffff, 0xffffffff)</ParentIdentifier>
			<BoxIdentifier>(0xffffffff, 0xffffffff)</BoxIdentifier>
			<NumChildren>1</NumChildren>
			<Attributes>
				<Attribute>
					<Identifier>(0x4c90d4ad, 0x7a2554ec)</Identifier>
					<Value>1</Value>
				</Attribute>
				<Attribute>
					<Identifier>(0x7b814cca, 0x271df6dd)</Identifier>
					<Value>1</Value>
				</Attribute>
			</Attributes>
		</VisualisationWidget>
		<VisualisationWidget>
			<Identifier>(0x3c5d4877, 0x0acb676d)</Identifier>
			<Name>Default tab</Name>
			<Type>2</Type>
			<ParentIdentifier>(0x77dc7174, 0x49113dde)</ParentIdentifier>
			<Index>0</Index>
			<BoxIdentifier>(0xffffffff, 0xffffffff)</BoxIdentifier>
			<NumChildren>1</NumChildren>
		</VisualisationWidget>
		<VisualisationWidget>
			<Identifier>(0x323268f8, 0x7e55ee3a)</Identifier>
			<Name>Empty</Name>
			<Type>0</Type>
			<ParentIdentifier>(0x3c5d4877, 0x0acb676d)</ParentIdentifier>
			<Index>0</Index>
			<BoxIdentifier>(0xffffffff, 0xffffffff)</BoxIdentifier>
			<NumChildren>0</NumChildren>
		</VisualisationWidget>
	</VisualisationTree>
</OpenViBE-Scenario>